sharepoint_online/__init__.py
sharepoint_online/auth.py
sharepoint_online/sharepoint.py
sharepoint_online_python_jamesgrogantech-0.0.6.dist-info/LICENSE
sharepoint_online_python_jamesgrogantech-0.0.6.dist-info/METADATA
sharepoint_online_python_jamesgrogantech-0.0.6.dist-info/WHEEL
sharepoint_online_python_jamesgrogantech-0.0.6.dist-info/top_level.txt
sharepoint_online_python_jamesgrogantech-0.0.6.dist-info/RECORD
