Metadata-Version: 2.1
Name: sharepoint-online-python-jamesgrogantech
Version: 0.0.6
Summary: Allows users to access Sharepoint data within a locally running Python script.
Home-page: https://github.com/jamesgrogantech/sharepoint-online-python
Author: James Grogan
Author-email: james@grogan.tech
License: MIT License
Project-URL: Bug Tracker, https://github.com/jamesgrogantech/sharepoint-online-python/issues
Platform: UNKNOWN
Classifier: Programming Language :: Python :: 3
Classifier: License :: OSI Approved :: MIT License
Classifier: Operating System :: OS Independent
Classifier: Development Status :: 3 - Alpha
Classifier: Topic :: Internet :: WWW/HTTP
Requires-Python: >=3.6
License-File: LICENSE
